nifki/__init__.py
nifki/__main__.py
nifki-0.1.dist-info/METADATA
nifki-0.1.dist-info/WHEEL
nifki-0.1.dist-info/entry_points.txt
nifki-0.1.dist-info/top_level.txt
nifki-0.1.dist-info/RECORD
