Metadata-Version: 2.4
Name: nifki
Version: 0.1
Summary: Python Nifki server
Author-email: Alistair Turnbull <apt1002@minworks.co.uk>, Tom Lynn <tom@beasts.org>, Reuben Thomas <rrt@sc3d.org>
License-Expression: GPL-3.0-or-later
Project-URL: Homepage, https://github.com/nifki/python-nifki
Classifier: Environment :: Web Environment
Classifier: Programming Language :: Python :: 3
Requires-Python: >=3.13
Requires-Dist: cherrypy
Requires-Dist: mistletoe
